AmatsukamiLogger/__init__.py
AmatsukamiLogger/base_logger.py
AmatsukamiLogger/json_logs_handler.py
AmatsukamiLogger/local_logs_handler.py
AmatsukamiLogger/loguru_forwarder.py
amatsukamilogger-0.1.2.dist-info/METADATA
amatsukamilogger-0.1.2.dist-info/WHEEL
amatsukamilogger-0.1.2.dist-info/top_level.txt
amatsukamilogger-0.1.2.dist-info/RECORD
